{
  "id": "sects-and-violets",
  "name": "Sects & Violets",
  "chineseName": "教派与紫罗兰",
  "roles": [
    {
      "id": "clockmaker",
      "name": "Clockmaker",
      "chineseName": "钟表匠",
      "team": "townsfolk",
      "summary": "You start knowing how many steps from the Demon to its nearest Minion.",
      "chineseSummary": "首夜：得知恶魔与最近爪牙之间相隔几步。",
      "detail": "First night only. Learn the distance between the Demon and the nearest Minion.",
      "chineseDetail": "仅首夜获知恶魔到最近爪牙的座位距离。",
      "icon": "person.fill.questionmark",
      "firstNight": true,
      "otherNights": false,
      "otherNightsExceptFirst": false,
      "targetCountFirstNight": 0,
      "targetCountNight": 0,
      "needsNightResultInput": true
    },
    {
      "id": "dreamer",
      "name": "Dreamer",
      "chineseName": "梦想家",
      "team": "townsfolk",
      "summary": "Each night, choose a player: you learn 1 good and 1 evil character, one of which is correct.",
      "chineseSummary": "每晚：选择一名玩家，得知 1 个善良角色和 1 个邪恶角色，其中 1 个正确。",
      "detail": "Wake each night and choose a player. The Storyteller shows one good and one evil character, with one matching the target.",
      "chineseDetail": "每晚查看一名玩家，并在一个善良角色与一个邪恶角色之间得到真假混合信息。",
      "icon": "person.fill.questionmark",
      "firstNight": true,
      "otherNights": true,
      "otherNightsExceptFirst": false,
      "targetCountFirstNight": 1,
      "targetCountNight": 1,
      "needsNightResultInput": true
    },
    {
      "id": "snake-charmer",
      "name": "Snake Charmer",
      "chineseName": "驯蛇人",
      "team": "townsfolk",
      "summary": "Each night, choose a player: if they are the Demon, you swap characters and alignments.",
      "chineseSummary": "每晚：选择一名玩家。若其是恶魔，你们交换角色与阵营。",
      "detail": "Choose a player each night. If they are the Demon, you become the Demon and they become the Snake Charmer.",
      "chineseDetail": "每晚指定一名玩家；若其是恶魔，则你们交换角色和阵营。",
      "icon": "person.fill.questionmark",
      "firstNight": true,
      "otherNights": true,
      "otherNightsExceptFirst": false,
      "targetCountFirstNight": 1,
      "targetCountNight": 1,
      "needsNightResultInput": true
    },
    {
      "id": "mathematician",
      "name": "Mathematician",
      "chineseName": "数学家",
      "team": "townsfolk",
      "summary": "Each night, learn how many players' abilities worked abnormally today or tonight.",
      "chineseSummary": "每晚：得知今天或今夜有多少玩家的能力异常生效。",
      "detail": "Wake each night and learn a number reflecting unusual ability resolution.",
      "chineseDetail": "每晚得到一个数字，代表今天或今夜有多少角色能力异常生效。",
      "icon": "person.fill.questionmark",
      "firstNight": true,
      "otherNights": true,
      "otherNightsExceptFirst": false,
      "targetCountFirstNight": 0,
      "targetCountNight": 0,
      "needsNightResultInput": true
    },
    {
      "id": "flowergirl",
      "name": "Flowergirl",
      "chineseName": "卖花女",
      "team": "townsfolk",
      "summary": "Each night*, learn if the Demon voted today.",
      "chineseSummary": "每晚（首夜除外）：得知恶魔今天是否投过票。",
      "detail": "On nights after the first, learn whether the Demon cast a vote during the day.",
      "chineseDetail": "首夜后每晚得知恶魔白天是否投票。",
      "icon": "person.fill.questionmark",
      "firstNight": false,
      "otherNights": true,
      "otherNightsExceptFirst": true,
      "targetCountFirstNight": 0,
      "targetCountNight": 0,
      "needsNightResultInput": true
    },
    {
      "id": "town-crier",
      "name": "Town Crier",
      "chineseName": "传令官",
      "team": "townsfolk",
      "summary": "Each night*, learn if a Minion nominated today.",
      "chineseSummary": "每晚（首夜除外）：得知今天是否有爪牙发起提名。",
      "detail": "On nights after the first, learn whether any Minion made a nomination during the day.",
      "chineseDetail": "首夜后每晚得知白天是否有爪牙提出提名。",
      "icon": "person.fill.questionmark",
      "firstNight": false,
      "otherNights": true,
      "otherNightsExceptFirst": true,
      "targetCountFirstNight": 0,
      "targetCountNight": 0,
      "needsNightResultInput": true
    },
    {
      "id": "oracle",
      "name": "Oracle",
      "chineseName": "神谕者",
      "team": "townsfolk",
      "summary": "Each night*, learn how many dead players are evil.",
      "chineseSummary": "每晚（首夜除外）：得知死去玩家中有多少是邪恶。",
      "detail": "On nights after the first, learn how many dead players are evil.",
      "chineseDetail": "首夜后每晚得知死者中邪恶玩家的数量。",
      "icon": "person.fill.questionmark",
      "firstNight": false,
      "otherNights": true,
      "otherNightsExceptFirst": true,
      "targetCountFirstNight": 0,
      "targetCountNight": 0,
      "needsNightResultInput": true
    },
    {
      "id": "savant",
      "name": "Savant",
      "chineseName": "博学者",
      "team": "townsfolk",
      "summary": "Each day, you may get 2 statements: 1 is true and 1 is false.",
      "chineseSummary": "每天：你可以获得两条陈述，其中一真一假。",
      "detail": "Daytime information role. The Storyteller offers two statements, one true and one false.",
      "chineseDetail": "白天由说书人给出两条陈述，一真一假，需自行辨别。",
      "icon": "person.fill.questionmark",
      "firstNight": false,
      "otherNights": false,
      "otherNightsExceptFirst": false,
      "targetCountFirstNight": 0,
      "targetCountNight": 0,
      "needsNightResultInput": false
    },
    {
      "id": "seamstress",
      "name": "Seamstress",
      "chineseName": "裁缝",
      "team": "townsfolk",
      "summary": "Once per game, at night, choose 2 players: you learn if they are the same alignment.",
      "chineseSummary": "每局一次，夜里：选择两名玩家，得知他们是否同阵营。",
      "detail": "One-shot night ability. Pick two players and learn whether their alignments match.",
      "chineseDetail": "一次性夜晚指定两名玩家，得知他们阵营是否相同。",
      "icon": "person.fill.questionmark",
      "firstNight": true,
      "otherNights": true,
      "otherNightsExceptFirst": false,
      "targetCountFirstNight": 2,
      "targetCountNight": 2,
      "needsNightResultInput": true
    },
    {
      "id": "philosopher",
      "name": "Philosopher",
      "chineseName": "哲学家",
      "team": "townsfolk",
      "summary": "Once per game, at night, choose a good character: gain that ability. If it is in play, that player is drunk.",
      "chineseSummary": "每局一次，夜里：选择一个善良角色并获得其能力；若该角色在场，则其醉酒。",
      "detail": "One-shot night choice. The Philosopher gains a chosen good character's ability; if that character is in play, they become drunk.",
      "chineseDetail": "一次性夜里选择一个善良角色来获得其能力；若该角色在场，则其醉酒。",
      "icon": "person.fill.questionmark",
      "firstNight": true,
      "otherNights": true,
      "otherNightsExceptFirst": false,
      "targetCountFirstNight": 0,
      "targetCountNight": 0,
      "needsNightResultInput": true
    },
    {
      "id": "artist",
      "name": "Artist",
      "chineseName": "艺术家",
      "team": "townsfolk",
      "summary": "Once per game, during the day, ask any yes/no question.",
      "chineseSummary": "每局一次，白天：提出任意一个是/否问题。",
      "detail": "One-shot daytime question. The Storyteller answers honestly.",
      "chineseDetail": "一次性白天向说书人提出任意一个是/否问题，获得真实回答。",
      "icon": "person.fill.questionmark",
      "firstNight": false,
      "otherNights": false,
      "otherNightsExceptFirst": false,
      "targetCountFirstNight": 0,
      "targetCountNight": 0,
      "needsNightResultInput": false
    },
    {
      "id": "juggler",
      "name": "Juggler",
      "chineseName": "杂耍演员",
      "team": "townsfolk",
      "summary": "On your first day, publicly guess up to 5 players' characters. That night, you learn how many are correct.",
      "chineseSummary": "第一天白天：公开猜最多 5 名玩家的角色；当夜得知猜对了几个。",
      "detail": "The Juggler makes public guesses during the day, then learns a number that night.",
      "chineseDetail": "第一天公开猜最多 5 人的角色；当夜得知猜中几个。",
      "icon": "person.fill.questionmark",
      "firstNight": false,
      "otherNights": true,
      "otherNightsExceptFirst": false,
      "targetCountFirstNight": 0,
      "targetCountNight": 0,
      "needsNightResultInput": true
    },
    {
      "id": "sage",
      "name": "Sage",
      "chineseName": "贤者",
      "team": "townsfolk",
      "summary": "If the Demon kills you, you learn that it is 1 of 2 players.",
      "chineseSummary": "若被恶魔杀死：得知两名玩家，其中一人是恶魔。",
      "detail": "If the Sage dies by the Demon, wake and learn two players, one of whom is the Demon.",
      "chineseDetail": "若被恶魔所杀，则在夜里获知两名玩家，其中一人是恶魔。",
      "icon": "person.fill.questionmark",
      "firstNight": false,
      "otherNights": true,
      "otherNightsExceptFirst": false,
      "targetCountFirstNight": 0,
      "targetCountNight": 2,
      "needsNightResultInput": true
    },
    {
      "id": "mutant",
      "name": "Mutant",
      "chineseName": "变种人",
      "team": "outsider",
      "summary": "If you are mad about being an Outsider, you might be executed.",
      "chineseSummary": "若你因自己是外来者而发疯失控，可能会被处决。",
      "detail": "Passive drawback. If the Mutant breaks madness about being an Outsider, the Storyteller may execute them.",
      "chineseDetail": "变种人若在发疯约束下暴露自己是外来者，可能会被说书人处决。",
      "icon": "person.fill.questionmark",
      "firstNight": false,
      "otherNights": false,
      "otherNightsExceptFirst": false,
      "targetCountFirstNight": 0,
      "targetCountNight": 0,
      "needsNightResultInput": false
    },
    {
      "id": "sweetheart",
      "name": "Sweetheart",
      "chineseName": "甜心",
      "team": "outsider",
      "summary": "When you die, 1 player is drunk from now on.",
      "chineseSummary": "当你死亡时，一名玩家从此醉酒。",
      "detail": "When the Sweetheart dies, one player becomes drunk permanently.",
      "chineseDetail": "死亡时会让一名玩家永久醉酒，由说书人决定。",
      "icon": "person.fill.questionmark",
      "firstNight": false,
      "otherNights": false,
      "otherNightsExceptFirst": false,
      "targetCountFirstNight": 0,
      "targetCountNight": 0,
      "needsNightResultInput": false
    },
    {
      "id": "barber",
      "name": "Barber",
      "chineseName": "理发师",
      "team": "outsider",
      "summary": "If you die, the Demon may swap 2 players' characters.",
      "chineseSummary": "当你死亡时，恶魔可以交换两名玩家的角色。",
      "detail": "On the Barber's death, the Demon may force a character swap between two players.",
      "chineseDetail": "理发师死亡后，恶魔可要求交换两名玩家的角色身份。",
      "icon": "person.fill.questionmark",
      "firstNight": false,
      "otherNights": false,
      "otherNightsExceptFirst": false,
      "targetCountFirstNight": 0,
      "targetCountNight": 0,
      "needsNightResultInput": false
    },
    {
      "id": "klutz",
      "name": "Klutz",
      "chineseName": "笨蛋",
      "team": "outsider",
      "summary": "When you learn that you died by execution, publicly choose 1 alive player: if they are evil, your team loses.",
      "chineseSummary": "当你得知自己被处决而死后，公开选择一名存活玩家；若其是邪恶，善良输。",
      "detail": "On execution death, the Klutz must choose a living player. If that player is evil, good loses.",
      "chineseDetail": "被处决死亡后必须公开点一名存活玩家；若其为邪恶，善良立刻失败。",
      "icon": "person.fill.questionmark",
      "firstNight": false,
      "otherNights": false,
      "otherNightsExceptFirst": false,
      "targetCountFirstNight": 0,
      "targetCountNight": 0,
      "needsNightResultInput": false
    },
    {
      "id": "evil-twin",
      "name": "Evil Twin",
      "chineseName": "邪恶双子",
      "team": "minion",
      "summary": "You and an opposing player know each other. If the good twin dies, evil wins. If the evil twin dies, good can't lose.",
      "chineseSummary": "你与一名对立阵营玩家互知。若善良双子死亡，邪恶赢；若邪恶双子死亡，善良不会输。",
      "detail": "First night only. The Evil Twin and a good player learn each other. The game is constrained until one dies.",
      "chineseDetail": "首夜互知。只要双子都活着，胜负会受其存亡强烈影响。",
      "icon": "person.fill.questionmark",
      "firstNight": true,
      "otherNights": false,
      "otherNightsExceptFirst": false,
      "targetCountFirstNight": 1,
      "targetCountNight": 0,
      "needsNightResultInput": true
    },
    {
      "id": "witch",
      "name": "Witch",
      "chineseName": "女巫",
      "team": "minion",
      "summary": "Each night, choose a player. If they nominate tomorrow, they die.",
      "chineseSummary": "每晚：选择一名玩家。若其明天提名，则立刻死亡。",
      "detail": "Choose a player each night. If that player nominates the next day, they die immediately.",
      "chineseDetail": "每晚指定一名玩家；若其明天提名，就会因女巫诅咒而死。",
      "icon": "person.fill.questionmark",
      "firstNight": false,
      "otherNights": true,
      "otherNightsExceptFirst": false,
      "targetCountFirstNight": 0,
      "targetCountNight": 1,
      "needsNightResultInput": false
    },
    {
      "id": "cerenovus",
      "name": "Cerenovus",
      "chineseName": "塞雷诺维斯",
      "team": "minion",
      "summary": "Each night, choose a player & a good character: they are mad they are that character tomorrow, or might be executed.",
      "chineseSummary": "每晚：选择一名玩家与一个善良角色；其明天必须对该角色发疯，否则可能被处决。",
      "detail": "Choose a player and a good character each night. The target must act mad as that character the next day.",
      "chineseDetail": "每晚指定一名玩家及一个善良角色；目标第二天必须对该角色发疯，否则可能被处决。",
      "icon": "person.fill.questionmark",
      "firstNight": false,
      "otherNights": true,
      "otherNightsExceptFirst": false,
      "targetCountFirstNight": 0,
      "targetCountNight": 1,
      "needsNightResultInput": true
    },
    {
      "id": "pit-hag",
      "name": "Pit-Hag",
      "chineseName": "坑巫",
      "team": "minion",
      "summary": "Each night*, choose a player & a character they become. If not in play, the Demon may make an extra death.",
      "chineseSummary": "每晚（首夜除外）：选择一名玩家及其将变成的角色。若合法则其转变；恶魔可能额外造成死亡。",
      "detail": "On nights after the first, transform a player into a chosen character if legal. Storyteller resolves extra deaths if needed.",
      "chineseDetail": "首夜后每晚可让一名玩家变成另一个角色；若出现非法局面，说书人以额外死亡等方式修正。",
      "icon": "person.fill.questionmark",
      "firstNight": false,
      "otherNights": true,
      "otherNightsExceptFirst": true,
      "targetCountFirstNight": 0,
      "targetCountNight": 1,
      "needsNightResultInput": true
    },
    {
      "id": "fang-gu",
      "name": "Fang Gu",
      "chineseName": "方固",
      "team": "demon",
      "summary": "Each night*, choose a player: they die. The 1st Outsider this kills becomes an evil Fang Gu & you die instead. [+1 Outsider]",
      "chineseSummary": "每晚（首夜除外）：选择一名玩家死亡。第一次被你杀死的外来者会转成邪恶方固，而你改为死亡。[+1 外来者]",
      "detail": "Night kill except the first. The first Outsider killed by the Fang Gu becomes the new evil Fang Gu, and the old one dies. Setup adds one Outsider.",
      "chineseDetail": "开局要额外加入 1 名外来者。首个被方固杀死的外来者会转为新的邪恶方固，而旧方固死亡。",
      "icon": "person.fill.questionmark",
      "firstNight": false,
      "otherNights": true,
      "otherNightsExceptFirst": true,
      "targetCountFirstNight": 0,
      "targetCountNight": 1,
      "needsNightResultInput": true
    },
    {
      "id": "vigormortis",
      "name": "Vigormortis",
      "chineseName": "维戈莫提斯",
      "team": "demon",
      "summary": "Each night*, choose a player: they die. Minions you kill keep their ability and poison their Townsfolk neighbors.",
      "chineseSummary": "每晚（首夜除外）：选择一名玩家死亡。被你杀死的爪牙保留能力，并毒化其相邻镇民。",
      "detail": "Night kill except the first. Killed Minions retain ability and may poison Townsfolk neighbors per Storyteller resolution.",
      "chineseDetail": "首夜后每晚杀一人；被其杀死的爪牙依旧保留能力，并毒化相邻镇民。",
      "icon": "person.fill.questionmark",
      "firstNight": false,
      "otherNights": true,
      "otherNightsExceptFirst": true,
      "targetCountFirstNight": 0,
      "targetCountNight": 1,
      "needsNightResultInput": true
    },
    {
      "id": "no-dashii",
      "name": "No Dashii",
      "chineseName": "诺达希",
      "team": "demon",
      "summary": "Each night*, choose a player: they die. Your 2 Townsfolk neighbors are poisoned.",
      "chineseSummary": "每晚（首夜除外）：选择一名玩家死亡。你的两侧镇民邻座会中毒。",
      "detail": "Night kill except the first. The No Dashii poisons its two Townsfolk neighbors while alive.",
      "chineseDetail": "首夜后每晚杀一人；其两侧镇民邻座持续中毒。",
      "icon": "person.fill.questionmark",
      "firstNight": false,
      "otherNights": true,
      "otherNightsExceptFirst": true,
      "targetCountFirstNight": 0,
      "targetCountNight": 1,
      "needsNightResultInput": true
    },
    {
      "id": "vortox",
      "name": "Vortox",
      "chineseName": "沃托克斯",
      "team": "demon",
      "summary": "Each night*, choose a player: they die. Townsfolk info is false. Good must execute each day or evil wins.",
      "chineseSummary": "每晚（首夜除外）：选择一名玩家死亡。镇民信息全错；善良每天必须处决，否则邪恶立胜。",
      "detail": "Night kill except the first. While alive, all Townsfolk information is false, and good must execute daily to avoid instant loss.",
      "chineseDetail": "首夜后每晚杀一人；镇民信息全部为假，且善良每天必须处决，否则邪恶立刻获胜。",
      "icon": "person.fill.questionmark",
      "firstNight": false,
      "otherNights": true,
      "otherNightsExceptFirst": true,
      "targetCountFirstNight": 0,
      "targetCountNight": 1,
      "needsNightResultInput": true
    }
  ],
  "nightOrderFirst": [
    {
      "id": "sv-first-clockmaker",
      "roleId": "clockmaker",
      "condition": "ifRoleInPlay",
      "conditionRoleId": "clockmaker"
    },
    {
      "id": "sv-first-dreamer",
      "roleId": "dreamer",
      "condition": "ifRoleInPlay",
      "conditionRoleId": "dreamer"
    },
    {
      "id": "sv-first-snake-charmer",
      "roleId": "snake-charmer",
      "condition": "ifRoleInPlay",
      "conditionRoleId": "snake-charmer"
    },
    {
      "id": "sv-first-mathematician",
      "roleId": "mathematician",
      "condition": "ifRoleInPlay",
      "conditionRoleId": "mathematician"
    },
    {
      "id": "sv-first-seamstress",
      "roleId": "seamstress",
      "condition": "ifRoleInPlay",
      "conditionRoleId": "seamstress"
    },
    {
      "id": "sv-first-philosopher",
      "roleId": "philosopher",
      "condition": "ifRoleInPlay",
      "conditionRoleId": "philosopher"
    },
    {
      "id": "sv-first-evil-twin",
      "roleId": "evil-twin",
      "condition": "ifRoleInPlay",
      "conditionRoleId": "evil-twin"
    }
  ],
  "nightOrderStandard": [
    {
      "id": "sv-night-dreamer",
      "roleId": "dreamer",
      "condition": "ifRoleInPlay",
      "conditionRoleId": "dreamer"
    },
    {
      "id": "sv-night-snake-charmer",
      "roleId": "snake-charmer",
      "condition": "ifRoleInPlay",
      "conditionRoleId": "snake-charmer"
    },
    {
      "id": "sv-night-mathematician",
      "roleId": "mathematician",
      "condition": "ifRoleInPlay",
      "conditionRoleId": "mathematician"
    },
    {
      "id": "sv-night-flowergirl",
      "roleId": "flowergirl",
      "condition": "ifRoleInPlay",
      "conditionRoleId": "flowergirl"
    },
    {
      "id": "sv-night-town-crier",
      "roleId": "town-crier",
      "condition": "ifRoleInPlay",
      "conditionRoleId": "town-crier"
    },
    {
      "id": "sv-night-oracle",
      "roleId": "oracle",
      "condition": "ifRoleInPlay",
      "conditionRoleId": "oracle"
    },
    {
      "id": "sv-night-seamstress",
      "roleId": "seamstress",
      "condition": "ifRoleInPlay",
      "conditionRoleId": "seamstress"
    },
    {
      "id": "sv-night-philosopher",
      "roleId": "philosopher",
      "condition": "ifRoleInPlay",
      "conditionRoleId": "philosopher"
    },
    {
      "id": "sv-night-juggler",
      "roleId": "juggler",
      "condition": "ifRoleInPlay",
      "conditionRoleId": "juggler"
    },
    {
      "id": "sv-night-sage",
      "roleId": "sage",
      "condition": "ifActorDiedTonight",
      "conditionRoleId": "sage"
    },
    {
      "id": "sv-night-witch",
      "roleId": "witch",
      "condition": "ifRoleInPlay",
      "conditionRoleId": "witch"
    },
    {
      "id": "sv-night-cerenovus",
      "roleId": "cerenovus",
      "condition": "ifRoleInPlay",
      "conditionRoleId": "cerenovus"
    },
    {
      "id": "sv-night-pit-hag",
      "roleId": "pit-hag",
      "condition": "ifRoleInPlay",
      "conditionRoleId": "pit-hag"
    },
    {
      "id": "sv-night-fang-gu",
      "roleId": "fang-gu",
      "condition": "ifRoleInPlay",
      "conditionRoleId": "fang-gu"
    },
    {
      "id": "sv-night-vigormortis",
      "roleId": "vigormortis",
      "condition": "ifRoleInPlay",
      "conditionRoleId": "vigormortis"
    },
    {
      "id": "sv-night-no-dashii",
      "roleId": "no-dashii",
      "condition": "ifRoleInPlay",
      "conditionRoleId": "no-dashii"
    },
    {
      "id": "sv-night-vortox",
      "roleId": "vortox",
      "condition": "ifRoleInPlay",
      "conditionRoleId": "vortox"
    }
  ]
}